Products.PasswordStrength-0.5.0-py3.9-nspkg.pth
Products/PasswordStrength/__init__.py
Products/PasswordStrength/configure.zcml
Products/PasswordStrength/interfaces.py
Products/PasswordStrength/plugin.py
Products/PasswordStrength/profiles.zcml
Products/PasswordStrength/setuphandlers.py
Products/PasswordStrength/testing.py
Products/PasswordStrength/locales/Products.PasswordStrength.pot
Products/PasswordStrength/locales/de/LC_MESSAGES/Products.PasswordStrength.po
Products/PasswordStrength/locales/es/LC_MESSAGES/Products.PasswordStrength.po
Products/PasswordStrength/locales/fr/LC_MESSAGES/Products.PasswordStrength.po
Products/PasswordStrength/overrides/Products.CMFPlone.browser.login.templates.pwreset_form.pt
Products/PasswordStrength/profiles/default/browserlayer.xml
Products/PasswordStrength/profiles/default/metadata.xml
Products/PasswordStrength/profiles/default/skins.xml
Products/PasswordStrength/profiles/uninstall/browserlayer.xml
Products/PasswordStrength/tests/__init__.py
Products/PasswordStrength/tests/backward_robot.py
Products/PasswordStrength/tests/password.robot
Products/PasswordStrength/tests/robot_setup.py
Products/PasswordStrength/tests/test_robot.py
Products/PasswordStrength/tests/test_setup.py
Products/PasswordStrength/www/passwordStrengthAdd.zpt
Products.PasswordStrength-0.5.0.dist-info/LICENSE.txt
Products.PasswordStrength-0.5.0.dist-info/METADATA
Products.PasswordStrength-0.5.0.dist-info/WHEEL
Products.PasswordStrength-0.5.0.dist-info/entry_points.txt
Products.PasswordStrength-0.5.0.dist-info/namespace_packages.txt
Products.PasswordStrength-0.5.0.dist-info/top_level.txt
Products.PasswordStrength-0.5.0.dist-info/RECORD
