Metadata-Version: 2.1
Name: Products.PasswordStrength
Version: 0.5.0
Summary: This Pluggable Authentication Service (PAS) plugin adds a password policy giving the possibility to define up to 5 regular expressions to validate a password. Default constrains are length, capital and lower letters, number and special characters.
Home-page: https://plone.org/products/passwordstrength
Author: Dylan Jay
Author-email: software@pretaweb.com
License: BSD
Keywords: PAS Plugins Zope password strength
Classifier: Development Status :: 5 - Production/Stable
Classifier: Environment :: Plugins
Classifier: Environment :: Web Environment
Classifier: Framework :: Plone :: 5.2
Classifier: Framework :: Plone :: 6.0
Classifier: Framework :: Zope2
Classifier: Intended Audience :: System Administrators
Classifier: License :: OSI Approved :: BSD License
Classifier: Operating System :: OS Independent
Classifier: Programming Language :: Python
Classifier: Programming Language :: Python :: 2.7
Classifier: Programming Language :: Python :: 3.6
Classifier: Programming Language :: Python :: 3.7
Classifier: Programming Language :: Python :: 3.8
Classifier: Programming Language :: Python :: 3.9
Classifier: Programming Language :: Zope
Classifier: Topic :: Software Development :: Libraries :: Python Modules
Classifier: Topic :: System :: Systems Administration
Classifier: Topic :: System :: Systems Administration :: Authentication/Directory
License-File: LICENSE.txt
Requires-Dist: setuptools
Requires-Dist: plone.api
Requires-Dist: collective.monkeypatcher
Requires-Dist: six
Requires-Dist: z3c.jbot
Provides-Extra: test
Requires-Dist: plone.app.robotframework; extra == "test"
Requires-Dist: plone.app.testing; extra == "test"
Requires-Dist: plone.browserlayer; extra == "test"
Requires-Dist: robotsuite; extra == "test"
